LICENSE
MANIFEST.in
README.md
setup.py
pywechat391019.egg-info/PKG-INFO
pywechat391019.egg-info/SOURCES.txt
pywechat391019.egg-info/dependency_links.txt
pywechat391019.egg-info/requires.txt
pywechat391019.egg-info/top_level.txt
wechat/__init__.py
wechat/core.py
wechat/events.py
wechat/logger.py
wechat/utils.py
wechat/tools/HPSocket4C.dll
wechat/tools/Helper_3.9.10.19.dll
wechat/tools/Loader_3.9.10.19.dll
wechat/tools/hook.exe
wechat/tools/start-wechat.exe